{
	"items": [
		{
			"_id": "5c6687d65e9d882c8841f0fd",
			"_tpl": "55d7217a4bdc2d86028b456d"
		},
		{
			"_id": "5c6687d65e9d882c8841f121",
			"_tpl": "557ffd194bdc2d28148b457f",
			"parentId": "5c6687d65e9d882c8841f0fd",
			"slotId": "Pockets"
		},
		{
			"_id": "5c6687d65e9d882c8841f0fc",
			"_tpl": "566abbc34bdc2d92178b4576"
		},
		{
			"_id": "5c6687d65e9d882c8841f0ff",
			"_tpl": "5963866b86f7747bfa1c4462"
		},
		{
			"_id": "5c6687d65e9d882c8841f0fe",
			"_tpl": "5963866286f7747bf429b572"
		},
		{
			"_id": "TacticalVest789288",
			"_tpl": "5d5d8ca986f7742798716522",
			"parentId": "5c6687d65e9d882c8841f0fd",
			"slotId": "TacticalVest"
		},
		{
			"_id": "I2101051107436183wcFmPWV",
			"_tpl": "59e6687d86f77411d949b251",
			"parentId": "5c6687d65e9d882c8841f0fd",
			"slotId": "FirstPrimaryWeapon"
		},
		{
			"_id": "I21010528013449756ssXEu6",
			"_tpl": "59e649f986f77411d949b246",
			"parentId": "I2101051107436183wcFmPWV",
			"slotId": "mod_gas_block"
		},
		{
			"_id": "I2101055643479719Mo6r1pU",
			"_tpl": "59e8a00d86f7742ad93b569c",
			"parentId": "I2101051107436183wcFmPWV",
			"slotId": "mod_muzzle"
		},
		{
			"_id": "I2101056404667664E3FteQB",
			"_tpl": "59e6318286f77444dd62c4cc",
			"parentId": "I2101051107436183wcFmPWV",
			"slotId": "mod_pistol_grip"
		},
		{
			"_id": "I2101059562075407NehXpGx",
			"_tpl": "59e8977386f77415a553c453",
			"parentId": "I2101051107436183wcFmPWV",
			"slotId": "mod_sight_rear",
			"upd": {
				"Sight": {
					"SelectedSightMode": 0
				}
			}
		},
		{
			"_id": "MagazineWeaponScav697",
			"_tpl": "5b1fd4e35acfc40018633c39",
			"parentId": "I2101051107436183wcFmPWV",
			"slotId": "mod_magazine"
		},
		{
			"_id": "AmmoMag14529",
			"_tpl": "59e6658b86f77411d949b250",
			"parentId": "MagazineWeaponScav697",
			"slotId": "cartridges",
			"upd": {
				"StackObjectsCount": 10
			}
		},
		{
			"_id": "I2101051710140599GSS3XJt",
			"_tpl": "59e898ee86f77427614bd225",
			"parentId": "I21010528013449756ssXEu6",
			"slotId": "mod_handguard"
		},
		{
			"_id": "mag0Vest26001",
			"_tpl": "5cfe8010d7ad1a59283b14c6",
			"parentId": "TacticalVest789288",
			"slotId": "2",
			"location": {
				"x": 0,
				"y": 0,
				"r": "Horizontal"
			}
		},
		{
			"_id": "AmmoMag0Vest724831",
			"_tpl": "59e6658b86f77411d949b250",
			"parentId": "mag0Vest26001",
			"slotId": "cartridges",
			"upd": {
				"StackObjectsCount": 50
			}
		},
		{
			"_id": "mag0Vest349003",
			"_tpl": "5cfe8010d7ad1a59283b14c6",
			"parentId": "TacticalVest789288",
			"slotId": "1",
			"location": {
				"x": 0,
				"y": 0,
				"r": "Horizontal"
			}
		},
		{
			"_id": "AmmoMag0Vest917995",
			"_tpl": "59e655cb86f77411dc52a77b",
			"parentId": "mag0Vest349003",
			"slotId": "cartridges",
			"upd": {
				"StackObjectsCount": 50
			}
		},
		{
			"_id": "mag0Vest623571",
			"_tpl": "5cfe8010d7ad1a59283b14c6",
			"parentId": "TacticalVest789288",
			"slotId": "1",
			"location": {
				"x": 1,
				"y": 0,
				"r": "Horizontal"
			}
		},
		{
			"_id": "AmmoMag0Vest151520",
			"_tpl": "59e6542b86f77411dc52a77a",
			"parentId": "mag0Vest623571",
			"slotId": "cartridges",
			"upd": {
				"StackObjectsCount": 50
			}
		},
		{
			"_id": "Scabbard473725",
			"_tpl": "57e26fc7245977162a14b800",
			"parentId": "5c6687d65e9d882c8841f0fd",
			"slotId": "Scabbard"
		},
		{
			"_id": "Headwear349486",
			"_tpl": "5aa2a7e8e5b5b00016327c16",
			"parentId": "5c6687d65e9d882c8841f0fd",
			"slotId": "Headwear"
		},
		{
			"_id": "FaceCover441144",
			"_tpl": "572b7f1624597762ae139822",
			"parentId": "5c6687d65e9d882c8841f0fd",
			"slotId": "FaceCover"
		},
		{
			"_id": "Backpack337255",
			"_tpl": "56e33634d2720bd8058b456b",
			"parentId": "5c6687d65e9d882c8841f0fd",
			"slotId": "Backpack"
		},
		{
			"_id": "BP_Backpack337255_348666",
			"_tpl": "5909e99886f7740c983b9984",
			"parentId": "Backpack337255",
			"slotId": "main",
			"location": {
				"x": 0,
				"y": 0,
				"r": "Horizontal"
			}
		},
		{
			"_id": "BP_Backpack337255_953491",
			"_tpl": "590c346786f77423e50ed342",
			"parentId": "Backpack337255",
			"slotId": "main",
			"location": {
				"x": 1,
				"y": 0,
				"r": "Horizontal"
			}
		},
		{
			"_id": "BP_Backpack337255_963003",
			"_tpl": "5d1b32c186f774252167a530",
			"parentId": "Backpack337255",
			"slotId": "main",
			"location": {
				"x": 0,
				"y": 1,
				"r": "Horizontal"
			}
		},
		{
			"_id": "BP_Backpack337255_484766",
			"_tpl": "5d1b31ce86f7742523398394",
			"parentId": "Backpack337255",
			"slotId": "main",
			"location": {
				"x": 2,
				"y": 0,
				"r": "Horizontal"
			}
		},
		{
			"_id": "BP_Backpack337255_398824",
			"_tpl": "5d1b309586f77425227d1676",
			"parentId": "Backpack337255",
			"slotId": "main",
			"location": {
				"x": 2,
				"y": 1,
				"r": "Horizontal"
			}
		},
		{
			"_id": "Pocket_938544",
			"_tpl": "590a358486f77429692b2790",
			"parentId": "5c6687d65e9d882c8841f121",
			"slotId": "pocket1",
			"location": {
				"x": 0,
				"y": 0,
				"r": "Horizontal"
			},
			"upd": {}
		},
		{
			"_id": "Pocket_51356",
			"_tpl": "573477e124597737dd42e191",
			"parentId": "5c6687d65e9d882c8841f121",
			"slotId": "pocket2",
			"location": {
				"x": 0,
				"y": 0,
				"r": "Horizontal"
			},
			"upd": {}
		}
	],
	"equipment": "5c6687d65e9d882c8841f0fd",
	"stash": "5c6687d65e9d882c8841f0fc",
	"questRaidItems": "5c6687d65e9d882c8841f0fe",
	"questStashItems": "5c6687d65e9d882c8841f0ff",
	"fastPanel": {}
}