{
	"items": [
		{
			"_id": "5c6687d65e9d882c8841f0fd",
			"_tpl": "55d7217a4bdc2d86028b456d"
		},
		{
			"_id": "5c6687d65e9d882c8841f121",
			"_tpl": "557ffd194bdc2d28148b457f",
			"parentId": "5c6687d65e9d882c8841f0fd",
			"slotId": "Pockets"
		},
		{
			"_id": "5c6687d65e9d882c8841f0fc",
			"_tpl": "566abbc34bdc2d92178b4576"
		},
		{
			"_id": "5c6687d65e9d882c8841f0ff",
			"_tpl": "5963866b86f7747bfa1c4462"
		},
		{
			"_id": "5c6687d65e9d882c8841f0fe",
			"_tpl": "5963866286f7747bf429b572"
		},
		{
			"_id": "TacticalVest863220",
			"_tpl": "5929a2a086f7744f4b234d43",
			"parentId": "5c6687d65e9d882c8841f0fd",
			"slotId": "TacticalVest"
		},
		{
			"_id": "I331017566325493301LxC5I",
			"_tpl": "5ab8e9fcd8ce870019439434",
			"upd": {
				"Repairable": {
					"MaxDurability": 100,
					"Durability": 100
				},
				"Foldable": {
					"Folded": false
				},
				"FireMode": {
					"FireMode": "single"
				}
			}
		},
		{
			"_id": "I331017562656159893BehIm",
			"_tpl": "59c6633186f7740cf0493bb9",
			"parentId": "I331017566325493301LxC5I",
			"slotId": "mod_gas_block"
		},
		{
			"_id": "I331017563912843506j3dZ5",
			"_tpl": "5649aa744bdc2ded0b8b457e",
			"parentId": "I331017566325493301LxC5I",
			"slotId": "mod_muzzle"
		},
		{
			"_id": "I331017568861032510ZaHn6",
			"_tpl": "57e3dba62459770f0c32322b",
			"parentId": "I331017566325493301LxC5I",
			"slotId": "mod_pistol_grip"
		},
		{
			"_id": "I331017565786653863i8rvV",
			"_tpl": "5649b0544bdc2d1b2b8b458a",
			"parentId": "I331017566325493301LxC5I",
			"slotId": "mod_sight_rear",
			"upd": {
				"Sight": {
					"SelectedSightMode": 0
				}
			}
		},
		{
			"_id": "MagazineWeaponScav3531",
			"_tpl": "55d4837c4bdc2d1d4e8b456c",
			"parentId": "I331017566325493301LxC5I",
			"slotId": "mod_magazine"
		},
		{
			"_id": "AmmoMag14959",
			"_tpl": "56dff2ced2720bb4668b4567",
			"parentId": "MagazineWeaponScav3531",
			"slotId": "cartridges",
			"upd": {
				"StackObjectsCount": 10
			}
		},
		{
			"_id": "I331017568563706759oc4F8",
			"_tpl": "5648b0744bdc2d363b8b4578",
			"parentId": "I331017562656159893BehIm",
			"slotId": "mod_handguard"
		},
		{
			"_id": "FuckYouUnlimitedAmmo753180",
			"_tpl": "5857a8bc2459772bad15db29",
			"parentId": "5c6687d65e9d882c8841f0fd",
			"slotId": "SecuredContainer"
		},
		{
			"_id": "iHateThatShit70392",
			"_tpl": "56dff026d2720bb8668b4567",
			"parentId": "FuckYouUnlimitedAmmo753180",
			"slotId": "main"
		},
		{
			"_id": "iHateThatShit390887",
			"_tpl": "56dff3afd2720bba668b4567",
			"parentId": "FuckYouUnlimitedAmmo753180",
			"slotId": "main"
		},
		{
			"_id": "iHateThatShit296445",
			"_tpl": "56dff338d2720bbd668b4569",
			"parentId": "FuckYouUnlimitedAmmo753180",
			"slotId": "main"
		},
		{
			"_id": "iHateThatShit196990",
			"_tpl": "56dff421d2720b5f5a8b4567",
			"parentId": "FuckYouUnlimitedAmmo753180",
			"slotId": "main"
		},
		{
			"_id": "iHateThatShit974402",
			"_tpl": "56dff4ecd2720b5f5a8b4568",
			"parentId": "FuckYouUnlimitedAmmo753180",
			"slotId": "main"
		},
		{
			"_id": "iHateThatShit738013",
			"_tpl": "5c0d5e4486f77478390952fe",
			"parentId": "FuckYouUnlimitedAmmo753180",
			"slotId": "main"
		},
		{
			"_id": "iHateThatShit412810",
			"_tpl": "5c0d5e4486f77478390952fe",
			"parentId": "FuckYouUnlimitedAmmo753180",
			"slotId": "main"
		},
		{
			"_id": "iHateThatShit139758",
			"_tpl": "56dff4ecd2720b5f5a8b4568",
			"parentId": "FuckYouUnlimitedAmmo753180",
			"slotId": "main"
		},
		{
			"_id": "iHateThatShit807013",
			"_tpl": "56dff061d2720bb5668b4567",
			"parentId": "FuckYouUnlimitedAmmo753180",
			"slotId": "main"
		},
		{
			"_id": "mag2Vest233347",
			"_tpl": "55d4837c4bdc2d1d4e8b456c",
			"parentId": "TacticalVest863220",
			"slotId": "5",
			"location": {
				"x": 0,
				"y": 0,
				"r": "Horizontal"
			}
		},
		{
			"_id": "AmmoMag2Vest478159",
			"_tpl": "5c0d5e4486f77478390952fe",
			"parentId": "mag2Vest233347",
			"slotId": "cartridges",
			"upd": {
				"StackObjectsCount": 10
			}
		},
		{
			"_id": "mag2Vest87989",
			"_tpl": "55d4837c4bdc2d1d4e8b456c",
			"parentId": "TacticalVest863220",
			"slotId": "5",
			"location": {
				"x": 0,
				"y": 1,
				"r": "Horizontal"
			}
		},
		{
			"_id": "AmmoMag2Vest177300",
			"_tpl": "56dfef82d2720bbd668b4567",
			"parentId": "mag2Vest87989",
			"slotId": "cartridges",
			"upd": {
				"StackObjectsCount": 10
			}
		},
		{
			"_id": "StackAmmo105022461",
			"_tpl": "56dff4ecd2720b5f5a8b4568",
			"parentId": "TacticalVest863220",
			"slotId": "1",
			"upd": {
				"StackObjectsCount": 14
			}
		},
		{
			"_id": "Scabbard196911",
			"_tpl": "57e26ea924597715ca604a09",
			"parentId": "5c6687d65e9d882c8841f0fd",
			"slotId": "Scabbard"
		},
		{
			"_id": "Headwear347859",
			"_tpl": "5a43943586f77416ad2f06e2",
			"parentId": "5c6687d65e9d882c8841f0fd",
			"slotId": "Headwear"
		},
		{
			"_id": "Eyewear399407",
			"_tpl": "557ff21e4bdc2d89578b4586",
			"parentId": "5c6687d65e9d882c8841f0fd",
			"slotId": "Eyewear"
		},
		{
			"_id": "Pocket_479465",
			"_tpl": "5af04b6486f774195a3ebb49",
			"parentId": "5c6687d65e9d882c8841f121",
			"slotId": "pocket1",
			"location": {
				"x": 0,
				"y": 0,
				"r": "Horizontal"
			},
			"upd": {
				"SpawnedInSession": true
			}
		}
	],
	"equipment": "5c6687d65e9d882c8841f0fd",
	"stash": "5c6687d65e9d882c8841f0fc",
	"questRaidItems": "5c6687d65e9d882c8841f0fe",
	"questStashItems": "5c6687d65e9d882c8841f0ff",
	"fastPanel": {}
}