{
	"items": [
		{
			"_id": "5c6687d65e9d882c8841f0fd",
			"_tpl": "55d7217a4bdc2d86028b456d"
		},
		{
			"_id": "5c6687d65e9d882c8841f121",
			"_tpl": "557ffd194bdc2d28148b457f",
			"parentId": "5c6687d65e9d882c8841f0fd",
			"slotId": "Pockets"
		},
		{
			"_id": "5c6687d65e9d882c8841f0fc",
			"_tpl": "566abbc34bdc2d92178b4576"
		},
		{
			"_id": "5c6687d65e9d882c8841f0ff",
			"_tpl": "5963866b86f7747bfa1c4462"
		},
		{
			"_id": "5c6687d65e9d882c8841f0fe",
			"_tpl": "5963866286f7747bf429b572"
		},
		{
			"_id": "TacticalVest751270",
			"_tpl": "5c0e446786f7742013381639",
			"parentId": "5c6687d65e9d882c8841f0fd",
			"slotId": "TacticalVest"
		},
		{
			"_id": "I331037216215836018jGtfq",
			"_tpl": "576165642459773c7a400233",
			"upd": {
				"Repairable": {
					"MaxDurability": 100,
					"Durability": 100
				},
				"Foldable": {
					"Folded": false
				},
				"FireMode": {
					"FireMode": "single"
				}
			}
		},
		{
			"_id": "I331037219561822274rTdbu",
			"_tpl": "576169e62459773c69055191",
			"parentId": "I331037216215836018jGtfq",
			"slotId": "mod_handguard"
		},
		{
			"_id": "I331037212680749283oTwUz",
			"_tpl": "576167ab2459773cad038c43",
			"parentId": "I331037216215836018jGtfq",
			"slotId": "mod_muzzle"
		},
		{
			"_id": "I331037214287133904UsXmw",
			"_tpl": "5649ade84bdc2d1b2b8b4587",
			"parentId": "I331037216215836018jGtfq",
			"slotId": "mod_pistol_grip"
		},
		{
			"_id": "I331037219819551362I4veV",
			"_tpl": "57a9b9ce2459770ee926038d",
			"parentId": "I331037216215836018jGtfq",
			"slotId": "mod_sight_rear",
			"upd": {
				"Sight": {
					"SelectedSightMode": 0
				}
			}
		},
		{
			"_id": "MagazineWeaponScav1916",
			"_tpl": "57616a9e2459773c7a400234",
			"parentId": "I331037216215836018jGtfq",
			"slotId": "mod_magazine"
		},
		{
			"_id": "AmmoMag16285",
			"_tpl": "5d6e68c4a4b9361b93413f79",
			"parentId": "MagazineWeaponScav1916",
			"slotId": "cartridges",
			"upd": {
				"StackObjectsCount": 5
			}
		},
		{
			"_id": "FuckYouUnlimitedAmmo452737",
			"_tpl": "5857a8bc2459772bad15db29",
			"parentId": "5c6687d65e9d882c8841f0fd",
			"slotId": "SecuredContainer"
		},
		{
			"_id": "iHateThatShit367285",
			"_tpl": "5d6e68e6a4b9361c140bcfe0",
			"parentId": "FuckYouUnlimitedAmmo452737",
			"slotId": "main"
		},
		{
			"_id": "iHateThatShit557579",
			"_tpl": "5d6e67fba4b9361bc73bc779",
			"parentId": "FuckYouUnlimitedAmmo452737",
			"slotId": "main"
		},
		{
			"_id": "iHateThatShit736907",
			"_tpl": "5d6e67fba4b9361bc73bc779",
			"parentId": "FuckYouUnlimitedAmmo452737",
			"slotId": "main"
		},
		{
			"_id": "iHateThatShit619410",
			"_tpl": "5c0d591486f7744c505b416f",
			"parentId": "FuckYouUnlimitedAmmo452737",
			"slotId": "main"
		},
		{
			"_id": "iHateThatShit115571",
			"_tpl": "5d6e6806a4b936088465b17e",
			"parentId": "FuckYouUnlimitedAmmo452737",
			"slotId": "main"
		},
		{
			"_id": "iHateThatShit608724",
			"_tpl": "5d6e68dea4b9361bcc29e659",
			"parentId": "FuckYouUnlimitedAmmo452737",
			"slotId": "main"
		},
		{
			"_id": "iHateThatShit74635",
			"_tpl": "5c0d591486f7744c505b416f",
			"parentId": "FuckYouUnlimitedAmmo452737",
			"slotId": "main"
		},
		{
			"_id": "iHateThatShit627516",
			"_tpl": "5d6e6911a4b9361bd5780d52",
			"parentId": "FuckYouUnlimitedAmmo452737",
			"slotId": "main"
		},
		{
			"_id": "iHateThatShit261593",
			"_tpl": "5d6e68d1a4b93622fe60e845",
			"parentId": "FuckYouUnlimitedAmmo452737",
			"slotId": "main"
		},
		{
			"_id": "mag1Vest710152",
			"_tpl": "57616a9e2459773c7a400234",
			"parentId": "TacticalVest751270",
			"slotId": "2",
			"location": {
				"x": 0,
				"y": 0,
				"r": "Horizontal"
			}
		},
		{
			"_id": "AmmoMag1Vest827329",
			"_tpl": "5d6e6806a4b936088465b17e",
			"parentId": "mag1Vest710152",
			"slotId": "cartridges",
			"upd": {
				"StackObjectsCount": 5
			}
		},
		{
			"_id": "mag2Vest210436",
			"_tpl": "57616a9e2459773c7a400234",
			"parentId": "TacticalVest751270",
			"slotId": "4",
			"location": {
				"x": 0,
				"y": 0,
				"r": "Horizontal"
			}
		},
		{
			"_id": "AmmoMag2Vest284928",
			"_tpl": "560d5e524bdc2d25448b4571",
			"parentId": "mag2Vest210436",
			"slotId": "cartridges",
			"upd": {
				"StackObjectsCount": 5
			}
		},
		{
			"_id": "StackAmmo35672855983",
			"_tpl": "5d6e6772a4b936088465b17c",
			"parentId": "TacticalVest751270",
			"slotId": "5",
			"upd": {
				"StackObjectsCount": 13
			}
		},
		{
			"_id": "Scabbard654343",
			"_tpl": "54491bb74bdc2d09088b4567",
			"parentId": "5c6687d65e9d882c8841f0fd",
			"slotId": "Scabbard"
		},
		{
			"_id": "Headwear522360",
			"_tpl": "5b4329075acfc400153b78ff",
			"parentId": "5c6687d65e9d882c8841f0fd",
			"slotId": "Headwear"
		},
		{
			"_id": "FaceCover841544",
			"_tpl": "5bd0716d86f774171822ef4b",
			"parentId": "5c6687d65e9d882c8841f0fd",
			"slotId": "FaceCover"
		},
		{
			"_id": "Pocket_541734",
			"_tpl": "5734773724597737fd047c14",
			"parentId": "5c6687d65e9d882c8841f121",
			"slotId": "pocket1",
			"location": {
				"x": 0,
				"y": 0,
				"r": "Horizontal"
			},
			"upd": {
				"SpawnedInSession": true
			}
		},
		{
			"_id": "Pocket_336783",
			"_tpl": "57347baf24597738002c6178",
			"parentId": "5c6687d65e9d882c8841f121",
			"slotId": "pocket2",
			"location": {
				"x": 0,
				"y": 0,
				"r": "Horizontal"
			},
			"upd": {
				"SpawnedInSession": true
			}
		},
		{
			"_id": "Pocket_952644",
			"_tpl": "5d1b3a5d86f774252167ba22",
			"parentId": "5c6687d65e9d882c8841f121",
			"slotId": "pocket3",
			"location": {
				"x": 0,
				"y": 0,
				"r": "Horizontal"
			},
			"upd": {
				"SpawnedInSession": true
			}
		}
	],
	"equipment": "5c6687d65e9d882c8841f0fd",
	"stash": "5c6687d65e9d882c8841f0fc",
	"questRaidItems": "5c6687d65e9d882c8841f0fe",
	"questStashItems": "5c6687d65e9d882c8841f0ff",
	"fastPanel": {}
}