{
	"items": [
		{
			"_id": "5c6687d65e9d882c8841f0fd",
			"_tpl": "55d7217a4bdc2d86028b456d"
		},
		{
			"_id": "5c6687d65e9d882c8841f121",
			"_tpl": "557ffd194bdc2d28148b457f",
			"parentId": "5c6687d65e9d882c8841f0fd",
			"slotId": "Pockets"
		},
		{
			"_id": "5c6687d65e9d882c8841f0fc",
			"_tpl": "566abbc34bdc2d92178b4576"
		},
		{
			"_id": "5c6687d65e9d882c8841f0ff",
			"_tpl": "5963866b86f7747bfa1c4462"
		},
		{
			"_id": "5c6687d65e9d882c8841f0fe",
			"_tpl": "5963866286f7747bf429b572"
		},
		{
			"_id": "TacticalVest521351",
			"_tpl": "5d5d646386f7742797261fd9",
			"parentId": "5c6687d65e9d882c8841f0fd",
			"slotId": "TacticalVest"
		},
		{
			"_id": "I210013502705308923ayhp4",
			"_tpl": "5de652c31b7e3716273428be",
			"parentId": "5c6687d65e9d882c8841f0fd",
			"slotId": "FirstPrimaryWeapon"
		},
		{
			"_id": "MagazineWeaponScav9247",
			"_tpl": "5de653abf76fdc1ce94a5a2a",
			"parentId": "I210013502705308923ayhp4",
			"slotId": "mod_magazine"
		},
		{
			"_id": "AmmoMag18154",
			"_tpl": "59e6542b86f77411dc52a77a",
			"parentId": "MagazineWeaponScav9247",
			"slotId": "cartridges",
			"upd": {
				"StackObjectsCount": 4
			}
		},
		{
			"_id": "I210013504198138994tT6uc",
			"_tpl": "5de655be4a9f347bc92edb88",
			"parentId": "I210013502705308923ayhp4",
			"slotId": "mod_stock"
		},
		{
			"_id": "I210013503604083775dsBDL",
			"_tpl": "5de65547883dde217541644b",
			"parentId": "I210013502705308923ayhp4",
			"slotId": "mod_barrel"
		},
		{
			"_id": "I210013508671591970MRz52",
			"_tpl": "5de6558e9f98ac2bc65950fc",
			"parentId": "I210013502705308923ayhp4",
			"slotId": "mod_mount"
		},
		{
			"_id": "I2100135084853553903uGeQ",
			"_tpl": "5de6556a205ddc616a6bc4f7",
			"parentId": "I210013503604083775dsBDL",
			"slotId": "mod_muzzle"
		},
		{
			"_id": "FuckYouUnlimitedAmmo336710",
			"_tpl": "5857a8bc2459772bad15db29",
			"parentId": "5c6687d65e9d882c8841f0fd",
			"slotId": "SecuredContainer"
		},
		{
			"_id": "iHateThatShit821986",
			"_tpl": "59e655cb86f77411dc52a77b",
			"parentId": "FuckYouUnlimitedAmmo336710"
		},
		{
			"_id": "iHateThatShit723791",
			"_tpl": "59e6542b86f77411dc52a77a",
			"parentId": "FuckYouUnlimitedAmmo336710"
		},
		{
			"_id": "iHateThatShit172884",
			"_tpl": "59e6658b86f77411d949b250",
			"parentId": "FuckYouUnlimitedAmmo336710"
		},
		{
			"_id": "iHateThatShit146007",
			"_tpl": "59e6658b86f77411d949b250",
			"parentId": "FuckYouUnlimitedAmmo336710"
		},
		{
			"_id": "iHateThatShit412569",
			"_tpl": "59e6542b86f77411dc52a77a",
			"parentId": "FuckYouUnlimitedAmmo336710"
		},
		{
			"_id": "iHateThatShit948819",
			"_tpl": "59e6658b86f77411d949b250",
			"parentId": "FuckYouUnlimitedAmmo336710"
		},
		{
			"_id": "iHateThatShit241294",
			"_tpl": "59e6542b86f77411dc52a77a",
			"parentId": "FuckYouUnlimitedAmmo336710"
		},
		{
			"_id": "iHateThatShit939236",
			"_tpl": "59e655cb86f77411dc52a77b",
			"parentId": "FuckYouUnlimitedAmmo336710"
		},
		{
			"_id": "iHateThatShit440570",
			"_tpl": "59e6658b86f77411d949b250",
			"parentId": "FuckYouUnlimitedAmmo336710"
		},
		{
			"_id": "mag0Vest280702",
			"_tpl": "5de653abf76fdc1ce94a5a2a",
			"parentId": "TacticalVest521351",
			"slotId": "3",
			"location": {
				"x": 0,
				"y": 0,
				"r": "Horizontal"
			}
		},
		{
			"_id": "AmmoMag0Vest847548",
			"_tpl": "59e655cb86f77411dc52a77b",
			"parentId": "mag0Vest280702",
			"slotId": "cartridges",
			"upd": {
				"StackObjectsCount": 4
			}
		},
		{
			"_id": "mag0Vest495103",
			"_tpl": "5de653abf76fdc1ce94a5a2a",
			"parentId": "TacticalVest521351",
			"slotId": "3",
			"location": {
				"x": 0,
				"y": 1,
				"r": "Horizontal"
			}
		},
		{
			"_id": "AmmoMag0Vest902145",
			"_tpl": "59e6658b86f77411d949b250",
			"parentId": "mag0Vest495103",
			"slotId": "cartridges",
			"upd": {
				"StackObjectsCount": 4
			}
		},
		{
			"_id": "mag1Vest918175",
			"_tpl": "5de653abf76fdc1ce94a5a2a",
			"parentId": "TacticalVest521351",
			"slotId": "5",
			"location": {
				"x": 0,
				"y": 1,
				"r": "Horizontal"
			}
		},
		{
			"_id": "AmmoMag1Vest833233",
			"_tpl": "59e6542b86f77411dc52a77a",
			"parentId": "mag1Vest918175",
			"slotId": "cartridges",
			"upd": {
				"StackObjectsCount": 4
			}
		},
		{
			"_id": "StackAmmo96872511687",
			"_tpl": "59e6542b86f77411dc52a77a",
			"parentId": "TacticalVest521351",
			"slotId": "7",
			"upd": {
				"StackObjectsCount": 48
			}
		},
		{
			"_id": "Scabbard884381",
			"_tpl": "5bffdc370db834001d23eca8",
			"parentId": "5c6687d65e9d882c8841f0fd",
			"slotId": "Scabbard"
		},
		{
			"_id": "Headwear729358",
			"_tpl": "572b7d8524597762b472f9d1",
			"parentId": "5c6687d65e9d882c8841f0fd",
			"slotId": "Headwear"
		},
		{
			"_id": "Eyewear469150",
			"_tpl": "5aa2b9aee5b5b00015693121",
			"parentId": "5c6687d65e9d882c8841f0fd",
			"slotId": "Eyewear"
		},
		{
			"_id": "Backpack181536",
			"_tpl": "5ab8f04f86f774585f4237d8",
			"parentId": "5c6687d65e9d882c8841f0fd",
			"slotId": "Backpack"
		},
		{
			"_id": "Pocket_38293",
			"_tpl": "5af0561e86f7745f5f3ad6ac",
			"parentId": "5c6687d65e9d882c8841f121",
			"slotId": "pocket1",
			"location": {
				"x": 0,
				"y": 0,
				"r": "Horizontal"
			},
			"upd": {
				"SpawnedInSession": true
			}
		}
	],
	"equipment": "5c6687d65e9d882c8841f0fd",
	"stash": "5c6687d65e9d882c8841f0fc",
	"questRaidItems": "5c6687d65e9d882c8841f0fe",
	"questStashItems": "5c6687d65e9d882c8841f0ff",
	"fastPanel": {}
}