{
	"items": [
		{
			"_id": "5c6687d65e9d882c8841f0fd",
			"_tpl": "55d7217a4bdc2d86028b456d"
		},
		{
			"_id": "5c6687d65e9d882c8841f121",
			"_tpl": "557ffd194bdc2d28148b457f",
			"parentId": "5c6687d65e9d882c8841f0fd",
			"slotId": "Pockets"
		},
		{
			"_id": "5c6687d65e9d882c8841f0fc",
			"_tpl": "566abbc34bdc2d92178b4576"
		},
		{
			"_id": "5c6687d65e9d882c8841f0ff",
			"_tpl": "5963866b86f7747bfa1c4462"
		},
		{
			"_id": "5c6687d65e9d882c8841f0fe",
			"_tpl": "5963866286f7747bf429b572"
		},
		{
			"_id": "TacticalVest929283",
			"_tpl": "5e4abfed86f77406a2713cf7",
			"parentId": "5c6687d65e9d882c8841f0fd",
			"slotId": "TacticalVest"
		},
		{
			"_id": "I3310435324897729316Lm6V",
			"_tpl": "5c07c60e0db834002330051f",
			"parentId": "5c6687d65e9d882c8841f0fd",
			"slotId": "FirstPrimaryWeapon"
		},
		{
			"_id": "I331043535597122964UsXFv",
			"_tpl": "5c0e2ff6d174af02a1659d4a",
			"parentId": "I3310435324897729316Lm6V",
			"slotId": "mod_pistol_grip"
		},
		{
			"_id": "MagazineWeaponScav6258",
			"_tpl": "55802d5f4bdc2dac148b458e",
			"parentId": "I3310435324897729316Lm6V",
			"slotId": "mod_magazine"
		},
		{
			"_id": "AmmoMag1848",
			"_tpl": "59e68f6f86f7746c9f75e846",
			"parentId": "MagazineWeaponScav6258",
			"slotId": "cartridges",
			"upd": {
				"StackObjectsCount": 30
			}
		},
		{
			"_id": "I331043535567692647mjekD",
			"_tpl": "5c0e2f26d174af02a9625114",
			"parentId": "I3310435324897729316Lm6V",
			"slotId": "mod_reciever"
		},
		{
			"_id": "I331043531679666971Dtt7U",
			"_tpl": "5649be884bdc2d79388b4577",
			"parentId": "I3310435324897729316Lm6V",
			"slotId": "mod_stock"
		},
		{
			"_id": "I3310435360514001462ajg1",
			"_tpl": "5c0faf68d174af02a96260b8",
			"parentId": "I3310435324897729316Lm6V",
			"slotId": "mod_charge"
		},
		{
			"_id": "I331043531394635896GJfYh",
			"_tpl": "584984812459776a704a82a6",
			"parentId": "I331043535567692647mjekD",
			"slotId": "mod_scope",
			"upd": {
				"Sight": {
					"SelectedSightMode": 0
				}
			}
		},
		{
			"_id": "I331043532874194583znWf7",
			"_tpl": "5c0e2f94d174af029f650d56",
			"parentId": "I331043535567692647mjekD",
			"slotId": "mod_barrel"
		},
		{
			"_id": "I331043532153226863sOo06",
			"_tpl": "5c0e2f5cd174af02a012cfc9",
			"parentId": "I331043535567692647mjekD",
			"slotId": "mod_handguard"
		},
		{
			"_id": "I331043534841265847CgUD7",
			"_tpl": "5c0fafb6d174af02a96260ba",
			"parentId": "I331043532874194583znWf7",
			"slotId": "mod_muzzle"
		},
		{
			"_id": "I331043533723833369dY3GS",
			"_tpl": "5ae30e795acfc408fb139a0b",
			"parentId": "I331043532874194583znWf7",
			"slotId": "mod_gas_block"
		},
		{
			"_id": "FuckYouUnlimitedAmmo38542",
			"_tpl": "5857a8bc2459772bad15db29",
			"parentId": "5c6687d65e9d882c8841f0fd",
			"slotId": "SecuredContainer"
		},
		{
			"_id": "iHateThatShit126601",
			"_tpl": "54527ac44bdc2d36668b4567",
			"parentId": "FuckYouUnlimitedAmmo38542",
			"slotId": "main"
		},
		{
			"_id": "iHateThatShit657712",
			"_tpl": "59e6906286f7746c9f75e847",
			"parentId": "FuckYouUnlimitedAmmo38542",
			"slotId": "main"
		},
		{
			"_id": "iHateThatShit754177",
			"_tpl": "59e6920f86f77411d82aa167",
			"parentId": "FuckYouUnlimitedAmmo38542",
			"slotId": "main"
		},
		{
			"_id": "iHateThatShit364711",
			"_tpl": "59e6906286f7746c9f75e847",
			"parentId": "FuckYouUnlimitedAmmo38542",
			"slotId": "main"
		},
		{
			"_id": "iHateThatShit716528",
			"_tpl": "59e6927d86f77411da468256",
			"parentId": "FuckYouUnlimitedAmmo38542",
			"slotId": "main"
		},
		{
			"_id": "iHateThatShit164103",
			"_tpl": "54527ac44bdc2d36668b4567",
			"parentId": "FuckYouUnlimitedAmmo38542",
			"slotId": "main"
		},
		{
			"_id": "iHateThatShit319313",
			"_tpl": "5c0d5ae286f7741e46554302",
			"parentId": "FuckYouUnlimitedAmmo38542",
			"slotId": "main"
		},
		{
			"_id": "iHateThatShit372815",
			"_tpl": "54527a984bdc2d4e668b4567",
			"parentId": "FuckYouUnlimitedAmmo38542",
			"slotId": "main"
		},
		{
			"_id": "iHateThatShit695941",
			"_tpl": "59e6918f86f7746c9f75e849",
			"parentId": "FuckYouUnlimitedAmmo38542",
			"slotId": "main"
		},
		{
			"_id": "mag1Vest526543",
			"_tpl": "5c6d42cb2e2216000e69d7d1",
			"parentId": "TacticalVest929283",
			"slotId": "2",
			"location": {
				"x": 0,
				"y": 0,
				"r": "Horizontal"
			}
		},
		{
			"_id": "AmmoMag1Vest321954",
			"_tpl": "59e6906286f7746c9f75e847",
			"parentId": "mag1Vest526543",
			"slotId": "cartridges",
			"upd": {
				"StackObjectsCount": 30
			}
		},
		{
			"_id": "Scabbard770005",
			"_tpl": "5bffdc370db834001d23eca8",
			"parentId": "5c6687d65e9d882c8841f0fd",
			"slotId": "Scabbard"
		},
		{
			"_id": "Headwear989831",
			"_tpl": "5a43943586f77416ad2f06e2",
			"parentId": "5c6687d65e9d882c8841f0fd",
			"slotId": "Headwear"
		},
		{
			"_id": "Backpack496619",
			"_tpl": "56e33634d2720bd8058b456b",
			"parentId": "5c6687d65e9d882c8841f0fd",
			"slotId": "Backpack"
		},
		{
			"_id": "BP_Backpack496619_499851",
			"_tpl": "57513f9324597720a7128161",
			"parentId": "Backpack496619",
			"slotId": "main",
			"location": {
				"x": 0,
				"y": 0,
				"r": "Horizontal"
			}
		},
		{
			"_id": "BP_Backpack496619_123719",
			"_tpl": "5938504186f7740991483f30",
			"parentId": "Backpack496619",
			"slotId": "main",
			"location": {
				"x": 0,
				"y": 2,
				"r": "Horizontal"
			}
		},
		{
			"_id": "BP_Backpack496619_395510",
			"_tpl": "5e2af22086f7746d3f3c33fa",
			"parentId": "Backpack496619",
			"slotId": "main",
			"location": {
				"x": 1,
				"y": 0,
				"r": "Horizontal"
			}
		},
		{
			"_id": "BP_Backpack496619_641272",
			"_tpl": "590c2b4386f77425357b6123",
			"parentId": "Backpack496619",
			"slotId": "main",
			"location": {
				"x": 1,
				"y": 1,
				"r": "Horizontal"
			}
		},
		{
			"_id": "BP_Backpack496619_357049",
			"_tpl": "59e366c186f7741778269d85",
			"parentId": "Backpack496619",
			"slotId": "main",
			"location": {
				"x": 1,
				"y": 2,
				"r": "Horizontal"
			}
		},
		{
			"_id": "BP_Backpack496619_101095",
			"_tpl": "5c13cef886f774072e618e82",
			"parentId": "Backpack496619",
			"slotId": "main",
			"location": {
				"x": 2,
				"y": 0,
				"r": "Horizontal"
			}
		},
		{
			"_id": "BP_Backpack496619_111665",
			"_tpl": "5734781f24597737e04bf32a",
			"parentId": "Backpack496619",
			"slotId": "main",
			"location": {
				"x": 2,
				"y": 1,
				"r": "Horizontal"
			}
		},
		{
			"_id": "ArmorVest305389",
			"_tpl": "5ab8e79e86f7742d8b372e78",
			"parentId": "5c6687d65e9d882c8841f0fd",
			"slotId": "ArmorVest",
			"upd": {
				"Repairable": {
					"MaxDurability": 65,
					"Durability": 9
				}
			}
		}
	],
	"equipment": "5c6687d65e9d882c8841f0fd",
	"stash": "5c6687d65e9d882c8841f0fc",
	"questRaidItems": "5c6687d65e9d882c8841f0fe",
	"questStashItems": "5c6687d65e9d882c8841f0ff",
	"fastPanel": {}
}