{
	"items": [
		{
			"_id": "5c6687d65e9d882c8841f0fd",
			"_tpl": "55d7217a4bdc2d86028b456d"
		},
		{
			"_id": "5c6687d65e9d882c8841f121",
			"_tpl": "557ffd194bdc2d28148b457f",
			"parentId": "5c6687d65e9d882c8841f0fd",
			"slotId": "Pockets"
		},
		{
			"_id": "5c6687d65e9d882c8841f0fc",
			"_tpl": "566abbc34bdc2d92178b4576"
		},
		{
			"_id": "5c6687d65e9d882c8841f0ff",
			"_tpl": "5963866b86f7747bfa1c4462"
		},
		{
			"_id": "5c6687d65e9d882c8841f0fe",
			"_tpl": "5963866286f7747bf429b572"
		},
		{
			"_id": "TacticalVest672416",
			"_tpl": "5d5d8ca986f7742798716522",
			"parentId": "5c6687d65e9d882c8841f0fd",
			"slotId": "TacticalVest"
		},
		{
			"_id": "I331039111891093725M1fGk",
			"_tpl": "59e6152586f77473dc057aa1",
			"upd": {
				"Repairable": {
					"MaxDurability": 100,
					"Durability": 100
				},
				"FireMode": {
					"FireMode": "single"
				}
			}
		},
		{
			"_id": "I331039113438145990rLJok",
			"_tpl": "59e649f986f77411d949b246",
			"parentId": "I331039111891093725M1fGk",
			"slotId": "mod_gas_block"
		},
		{
			"_id": "I3310391131779451889AvNB",
			"_tpl": "59e61eb386f77440d64f5daf",
			"parentId": "I331039111891093725M1fGk",
			"slotId": "mod_muzzle"
		},
		{
			"_id": "I331039113889363648YxDDG",
			"_tpl": "59e6318286f77444dd62c4cc",
			"parentId": "I331039111891093725M1fGk",
			"slotId": "mod_pistol_grip"
		},
		{
			"_id": "I331039111120446292tCxwF",
			"_tpl": "59d650cf86f7741b846413a4",
			"parentId": "I331039111891093725M1fGk",
			"slotId": "mod_sight_rear",
			"upd": {
				"Sight": {
					"SelectedSightMode": 0
				}
			}
		},
		{
			"_id": "I331039115421836859riXL9",
			"_tpl": "59e6227d86f77440d64f5dc2",
			"parentId": "I331039111891093725M1fGk",
			"slotId": "mod_stock"
		},
		{
			"_id": "MagazineWeaponScav1283",
			"_tpl": "5a01c29586f77474660c694c",
			"parentId": "I331039111891093725M1fGk",
			"slotId": "mod_magazine"
		},
		{
			"_id": "AmmoMag18939",
			"_tpl": "5656d7c34bdc2d9d198b4587",
			"parentId": "MagazineWeaponScav1283",
			"slotId": "cartridges",
			"upd": {
				"StackObjectsCount": 30
			}
		},
		{
			"_id": "I331039115170153350bLafO",
			"_tpl": "59e6284f86f77440d569536f",
			"parentId": "I331039113438145990rLJok",
			"slotId": "mod_handguard"
		},
		{
			"_id": "FuckYouUnlimitedAmmo989313",
			"_tpl": "5857a8bc2459772bad15db29",
			"parentId": "5c6687d65e9d882c8841f0fd",
			"slotId": "SecuredContainer"
		},
		{
			"_id": "iHateThatShit132709",
			"_tpl": "59e0d99486f7744a32234762",
			"parentId": "FuckYouUnlimitedAmmo989313"
		},
		{
			"_id": "iHateThatShit351729",
			"_tpl": "59e0d99486f7744a32234762",
			"parentId": "FuckYouUnlimitedAmmo989313"
		},
		{
			"_id": "iHateThatShit882313",
			"_tpl": "59e4cf5286f7741778269d8a",
			"parentId": "FuckYouUnlimitedAmmo989313"
		},
		{
			"_id": "iHateThatShit940932",
			"_tpl": "59e4d24686f7741776641ac7",
			"parentId": "FuckYouUnlimitedAmmo989313"
		},
		{
			"_id": "iHateThatShit707818",
			"_tpl": "59e4d24686f7741776641ac7",
			"parentId": "FuckYouUnlimitedAmmo989313"
		},
		{
			"_id": "iHateThatShit886376",
			"_tpl": "59e4d24686f7741776641ac7",
			"parentId": "FuckYouUnlimitedAmmo989313"
		},
		{
			"_id": "iHateThatShit118136",
			"_tpl": "59e0d99486f7744a32234762",
			"parentId": "FuckYouUnlimitedAmmo989313"
		},
		{
			"_id": "iHateThatShit335261",
			"_tpl": "59e4cf5286f7741778269d8a",
			"parentId": "FuckYouUnlimitedAmmo989313"
		},
		{
			"_id": "iHateThatShit31651",
			"_tpl": "5656d7c34bdc2d9d198b4587",
			"parentId": "FuckYouUnlimitedAmmo989313"
		},
		{
			"_id": "mag1Vest1917",
			"_tpl": "5a0060fc86f7745793204432",
			"parentId": "TacticalVest672416",
			"slotId": "3",
			"location": {
				"x": 0,
				"y": 0,
				"r": "Horizontal"
			}
		},
		{
			"_id": "AmmoMag1Vest717204",
			"_tpl": "59e0d99486f7744a32234762",
			"parentId": "mag1Vest1917",
			"slotId": "cartridges",
			"upd": {
				"StackObjectsCount": 30
			}
		},
		{
			"_id": "Scabbard69472",
			"_tpl": "57e26ea924597715ca604a09",
			"parentId": "5c6687d65e9d882c8841f0fd",
			"slotId": "Scabbard"
		},
		{
			"_id": "Headwear230309",
			"_tpl": "5aa2b8d7e5b5b00014028f4a",
			"parentId": "5c6687d65e9d882c8841f0fd",
			"slotId": "Headwear"
		},
		{
			"_id": "Pocket_775703",
			"_tpl": "5734795124597738002c6176",
			"parentId": "5c6687d65e9d882c8841f121",
			"slotId": "pocket1",
			"location": {
				"x": 0,
				"y": 0,
				"r": "Horizontal"
			},
			"upd": {
				"SpawnedInSession": true
			}
		},
		{
			"_id": "Pocket_810959",
			"_tpl": "5c13cef886f774072e618e82",
			"parentId": "5c6687d65e9d882c8841f121",
			"slotId": "pocket2",
			"location": {
				"x": 0,
				"y": 0,
				"r": "Horizontal"
			},
			"upd": {
				"SpawnedInSession": true
			}
		},
		{
			"_id": "Pocket_804121",
			"_tpl": "59e366c186f7741778269d85",
			"parentId": "5c6687d65e9d882c8841f121",
			"slotId": "pocket3",
			"location": {
				"x": 0,
				"y": 0,
				"r": "Horizontal"
			},
			"upd": {
				"SpawnedInSession": true
			}
		}
	],
	"equipment": "5c6687d65e9d882c8841f0fd",
	"stash": "5c6687d65e9d882c8841f0fc",
	"questRaidItems": "5c6687d65e9d882c8841f0fe",
	"questStashItems": "5c6687d65e9d882c8841f0ff",
	"fastPanel": {}
}