{
	"items": [
		{
			"_id": "5c6687d65e9d882c8841f0fd",
			"_tpl": "55d7217a4bdc2d86028b456d"
		},
		{
			"_id": "5c6687d65e9d882c8841f121",
			"_tpl": "557ffd194bdc2d28148b457f",
			"parentId": "5c6687d65e9d882c8841f0fd",
			"slotId": "Pockets"
		},
		{
			"_id": "5c6687d65e9d882c8841f0fc",
			"_tpl": "566abbc34bdc2d92178b4576"
		},
		{
			"_id": "5c6687d65e9d882c8841f0ff",
			"_tpl": "5963866b86f7747bfa1c4462"
		},
		{
			"_id": "5c6687d65e9d882c8841f0fe",
			"_tpl": "5963866286f7747bf429b572"
		},
		{
			"_id": "TacticalVest485679",
			"_tpl": "5648a69d4bdc2ded0b8b457b",
			"parentId": "5c6687d65e9d882c8841f0fd",
			"slotId": "TacticalVest"
		},
		{
			"_id": "I210050576156857912OZ9L7",
			"_tpl": "5abcbc27d8ce8700182eceeb",
			"parentId": "5c6687d65e9d882c8841f0fd",
			"slotId": "FirstPrimaryWeapon"
		},
		{
			"_id": "I210050573192892438O9mP4",
			"_tpl": "59d64ec286f774171d1e0a42",
			"parentId": "I210050576156857912OZ9L7",
			"slotId": "mod_gas_block"
		},
		{
			"_id": "I210050578472391306EX0F2",
			"_tpl": "59e61eb386f77440d64f5daf",
			"parentId": "I210050576156857912OZ9L7",
			"slotId": "mod_muzzle"
		},
		{
			"_id": "I210050572763710976gsnxk",
			"_tpl": "5a0071d486f77404e23a12b2",
			"parentId": "I210050576156857912OZ9L7",
			"slotId": "mod_pistol_grip_akms"
		},
		{
			"_id": "I210050577635509251cC44m",
			"_tpl": "59d650cf86f7741b846413a4",
			"parentId": "I210050576156857912OZ9L7",
			"slotId": "mod_sight_rear",
			"upd": {
				"Sight": {
					"SelectedSightMode": 0
				}
			}
		},
		{
			"_id": "I210050575505166963PRLEC",
			"_tpl": "59ff3b6a86f77477562ff5ed",
			"parentId": "I210050576156857912OZ9L7",
			"slotId": "mod_stock_akms"
		},
		{
			"_id": "MagazineWeaponScav1583",
			"_tpl": "59e5d83b86f7745aed03d262",
			"parentId": "I210050576156857912OZ9L7",
			"slotId": "mod_magazine"
		},
		{
			"_id": "AmmoMag12192",
			"_tpl": "59e4d3d286f774176a36250a",
			"parentId": "MagazineWeaponScav1583",
			"slotId": "cartridges",
			"upd": {
				"StackObjectsCount": 10
			}
		},
		{
			"_id": "I210050571279421349KWsNZ",
			"_tpl": "59d64f2f86f77417193ef8b3",
			"parentId": "I210050573192892438O9mP4",
			"slotId": "mod_handguard"
		},
		{
			"_id": "FuckYouUnlimitedAmmo616790",
			"_tpl": "5857a8bc2459772bad15db29",
			"parentId": "5c6687d65e9d882c8841f0fd",
			"slotId": "SecuredContainer"
		},
		{
			"_id": "iHateThatShit359519",
			"_tpl": "59e4cf5286f7741778269d8a",
			"parentId": "FuckYouUnlimitedAmmo616790",
			"slotId": "main"
		},
		{
			"_id": "iHateThatShit34469",
			"_tpl": "5656d7c34bdc2d9d198b4587",
			"parentId": "FuckYouUnlimitedAmmo616790",
			"slotId": "main"
		},
		{
			"_id": "iHateThatShit692185",
			"_tpl": "59e4d24686f7741776641ac7",
			"parentId": "FuckYouUnlimitedAmmo616790",
			"slotId": "main"
		},
		{
			"_id": "iHateThatShit251719",
			"_tpl": "59e4d24686f7741776641ac7",
			"parentId": "FuckYouUnlimitedAmmo616790",
			"slotId": "main"
		},
		{
			"_id": "iHateThatShit242483",
			"_tpl": "5656d7c34bdc2d9d198b4587",
			"parentId": "FuckYouUnlimitedAmmo616790",
			"slotId": "main"
		},
		{
			"_id": "iHateThatShit804377",
			"_tpl": "59e4cf5286f7741778269d8a",
			"parentId": "FuckYouUnlimitedAmmo616790",
			"slotId": "main"
		},
		{
			"_id": "iHateThatShit503109",
			"_tpl": "59e0d99486f7744a32234762",
			"parentId": "FuckYouUnlimitedAmmo616790",
			"slotId": "main"
		},
		{
			"_id": "iHateThatShit286344",
			"_tpl": "59e4cf5286f7741778269d8a",
			"parentId": "FuckYouUnlimitedAmmo616790",
			"slotId": "main"
		},
		{
			"_id": "iHateThatShit984445",
			"_tpl": "59e0d99486f7744a32234762",
			"parentId": "FuckYouUnlimitedAmmo616790",
			"slotId": "main"
		},
		{
			"_id": "mag0Vest767734",
			"_tpl": "59e5d83b86f7745aed03d262",
			"parentId": "TacticalVest485679",
			"slotId": "1",
			"location": {
				"x": 0,
				"y": 0,
				"r": "Horizontal"
			}
		},
		{
			"_id": "AmmoMag0Vest160605",
			"_tpl": "59e4cf5286f7741778269d8a",
			"parentId": "mag0Vest767734",
			"slotId": "cartridges",
			"upd": {
				"StackObjectsCount": 10
			}
		},
		{
			"_id": "mag0Vest797375",
			"_tpl": "59e5d83b86f7745aed03d262",
			"parentId": "TacticalVest485679",
			"slotId": "1",
			"location": {
				"x": 0,
				"y": 1,
				"r": "Horizontal"
			}
		},
		{
			"_id": "AmmoMag0Vest824053",
			"_tpl": "59e4cf5286f7741778269d8a",
			"parentId": "mag0Vest797375",
			"slotId": "cartridges",
			"upd": {
				"StackObjectsCount": 10
			}
		},
		{
			"_id": "mag1Vest307687",
			"_tpl": "59e5d83b86f7745aed03d262",
			"parentId": "TacticalVest485679",
			"slotId": "3",
			"location": {
				"x": 0,
				"y": 1,
				"r": "Horizontal"
			}
		},
		{
			"_id": "AmmoMag1Vest897553",
			"_tpl": "59e4d3d286f774176a36250a",
			"parentId": "mag1Vest307687",
			"slotId": "cartridges",
			"upd": {
				"StackObjectsCount": 10
			}
		},
		{
			"_id": "mag2Vest405810",
			"_tpl": "59e5d83b86f7745aed03d262",
			"parentId": "TacticalVest485679",
			"slotId": "10",
			"location": {
				"x": 0,
				"y": 1,
				"r": "Horizontal"
			}
		},
		{
			"_id": "AmmoMag2Vest530528",
			"_tpl": "59e0d99486f7744a32234762",
			"parentId": "mag2Vest405810",
			"slotId": "cartridges",
			"upd": {
				"StackObjectsCount": 10
			}
		},
		{
			"_id": "Scabbard173676",
			"_tpl": "57e26fc7245977162a14b800",
			"parentId": "5c6687d65e9d882c8841f0fd",
			"slotId": "Scabbard"
		},
		{
			"_id": "Headwear307307",
			"_tpl": "5aa2ba46e5b5b000137b758d",
			"parentId": "5c6687d65e9d882c8841f0fd",
			"slotId": "Headwear"
		},
		{
			"_id": "Eyewear800544",
			"_tpl": "59e770b986f7742cbd762754",
			"parentId": "5c6687d65e9d882c8841f0fd",
			"slotId": "Eyewear"
		},
		{
			"_id": "Backpack778373",
			"_tpl": "56e33634d2720bd8058b456b",
			"parentId": "5c6687d65e9d882c8841f0fd",
			"slotId": "Backpack"
		},
		{
			"_id": "BP_Backpack778373_313692",
			"_tpl": "573474f924597738002c6174",
			"parentId": "Backpack778373",
			"slotId": "main",
			"location": {
				"x": 0,
				"y": 0,
				"r": "Horizontal"
			}
		},
		{
			"_id": "Pocket_151543",
			"_tpl": "590a3c0a86f774385a33c450",
			"parentId": "5c6687d65e9d882c8841f121",
			"slotId": "pocket1",
			"location": {
				"x": 0,
				"y": 0,
				"r": "Horizontal"
			},
			"upd": {
				"SpawnedInSession": true
			}
		},
		{
			"_id": "Pocket_304089",
			"_tpl": "57347cd0245977445a2d6ff1",
			"parentId": "5c6687d65e9d882c8841f121",
			"slotId": "pocket2",
			"location": {
				"x": 0,
				"y": 0,
				"r": "Horizontal"
			},
			"upd": {
				"SpawnedInSession": true
			}
		},
		{
			"_id": "Pocket_971704",
			"_tpl": "5a0eecf686f7740350630097",
			"parentId": "5c6687d65e9d882c8841f121",
			"slotId": "pocket3",
			"location": {
				"x": 0,
				"y": 0,
				"r": "Horizontal"
			},
			"upd": {
				"SpawnedInSession": true
			}
		}
	],
	"equipment": "5c6687d65e9d882c8841f0fd",
	"stash": "5c6687d65e9d882c8841f0fc",
	"questRaidItems": "5c6687d65e9d882c8841f0fe",
	"questStashItems": "5c6687d65e9d882c8841f0ff",
	"fastPanel": {}
}