{
	"items": [
		{
			"_id": "5c6687d65e9d882c8841f0fd",
			"_tpl": "55d7217a4bdc2d86028b456d"
		},
		{
			"_id": "5c6687d65e9d882c8841f121",
			"_tpl": "557ffd194bdc2d28148b457f",
			"parentId": "5c6687d65e9d882c8841f0fd",
			"slotId": "Pockets"
		},
		{
			"_id": "5c6687d65e9d882c8841f0fc",
			"_tpl": "566abbc34bdc2d92178b4576"
		},
		{
			"_id": "5c6687d65e9d882c8841f0ff",
			"_tpl": "5963866b86f7747bfa1c4462"
		},
		{
			"_id": "5c6687d65e9d882c8841f0fe",
			"_tpl": "5963866286f7747bf429b572"
		},
		{
			"_id": "TacticalVest121709",
			"_tpl": "5c0e3eb886f7742015526062",
			"parentId": "5c6687d65e9d882c8841f0fd",
			"slotId": "TacticalVest"
		},
		{
			"_id": "I210013408127790895aIQlX",
			"_tpl": "5bfea6e90db834001b7347f3",
			"parentId": "5c6687d65e9d882c8841f0fd",
			"slotId": "FirstPrimaryWeapon"
		},
		{
			"_id": "MagazineWeaponScav9571",
			"_tpl": "5cf12a15d7f00c05464b293f",
			"parentId": "I210013408127790895aIQlX",
			"slotId": "mod_magazine"
		},
		{
			"_id": "AmmoMag16860",
			"_tpl": "5a6086ea4f39f99cd479502f",
			"parentId": "MagazineWeaponScav9571",
			"slotId": "cartridges",
			"upd": {
				"StackObjectsCount": 20
			}
		},
		{
			"_id": "I210013402784102846OF3LC",
			"_tpl": "5bfeb32b0db834001a6694d9",
			"parentId": "I210013408127790895aIQlX",
			"slotId": "mod_stock"
		},
		{
			"_id": "I210013407544258067pRHdV",
			"_tpl": "5bfebc320db8340019668d79",
			"parentId": "I210013408127790895aIQlX",
			"slotId": "mod_barrel"
		},
		{
			"_id": "FuckYouUnlimitedAmmo619273",
			"_tpl": "5857a8bc2459772bad15db29",
			"parentId": "5c6687d65e9d882c8841f0fd",
			"slotId": "SecuredContainer"
		},
		{
			"_id": "iHateThatShit627392",
			"_tpl": "5a608bf24f39f98ffc77720e",
			"parentId": "FuckYouUnlimitedAmmo619273",
			"slotId": "main"
		},
		{
			"_id": "iHateThatShit637084",
			"_tpl": "5a608bf24f39f98ffc77720e",
			"parentId": "FuckYouUnlimitedAmmo619273",
			"slotId": "main"
		},
		{
			"_id": "iHateThatShit970308",
			"_tpl": "5a608bf24f39f98ffc77720e",
			"parentId": "FuckYouUnlimitedAmmo619273",
			"slotId": "main"
		},
		{
			"_id": "iHateThatShit876325",
			"_tpl": "5e023e88277cce2b522ff2b1",
			"parentId": "FuckYouUnlimitedAmmo619273",
			"slotId": "main"
		},
		{
			"_id": "iHateThatShit796900",
			"_tpl": "5e023e53d4353e3302577c4c",
			"parentId": "FuckYouUnlimitedAmmo619273",
			"slotId": "main"
		},
		{
			"_id": "iHateThatShit79504",
			"_tpl": "5a608bf24f39f98ffc77720e",
			"parentId": "FuckYouUnlimitedAmmo619273",
			"slotId": "main"
		},
		{
			"_id": "iHateThatShit373251",
			"_tpl": "5a608bf24f39f98ffc77720e",
			"parentId": "FuckYouUnlimitedAmmo619273",
			"slotId": "main"
		},
		{
			"_id": "iHateThatShit731630",
			"_tpl": "5e023e88277cce2b522ff2b1",
			"parentId": "FuckYouUnlimitedAmmo619273",
			"slotId": "main"
		},
		{
			"_id": "iHateThatShit369409",
			"_tpl": "5e023e53d4353e3302577c4c",
			"parentId": "FuckYouUnlimitedAmmo619273",
			"slotId": "main"
		},
		{
			"_id": "mag2Vest415513",
			"_tpl": "5d25a6a48abbc306c62e6310",
			"parentId": "TacticalVest121709",
			"slotId": "3",
			"location": {
				"x": 0,
				"y": 0,
				"r": "Horizontal"
			}
		},
		{
			"_id": "AmmoMag2Vest471646",
			"_tpl": "58dd3ad986f77403051cba8f",
			"parentId": "mag2Vest415513",
			"slotId": "cartridges",
			"upd": {
				"StackObjectsCount": 12
			}
		},
		{
			"_id": "StackAmmo82345971060",
			"_tpl": "5a6086ea4f39f99cd479502f",
			"parentId": "TacticalVest121709",
			"slotId": "6",
			"upd": {
				"StackObjectsCount": 30
			}
		},
		{
			"_id": "Scabbard451956",
			"_tpl": "57e26fc7245977162a14b800",
			"parentId": "5c6687d65e9d882c8841f0fd",
			"slotId": "Scabbard"
		},
		{
			"_id": "Headwear909394",
			"_tpl": "5c08f87c0db8340019124324",
			"parentId": "5c6687d65e9d882c8841f0fd",
			"slotId": "Headwear"
		},
		{
			"_id": "FaceCover889007",
			"_tpl": "59e7715586f7742ee5789605",
			"parentId": "5c6687d65e9d882c8841f0fd",
			"slotId": "FaceCover"
		},
		{
			"_id": "ArmorVest777512",
			"_tpl": "5ab8e79e86f7742d8b372e78",
			"parentId": "5c6687d65e9d882c8841f0fd",
			"slotId": "ArmorVest",
			"upd": {
				"Repairable": {
					"MaxDurability": 65,
					"Durability": 37
				}
			}
		},
		{
			"_id": "Pocket_139598",
			"_tpl": "5913651986f774432f15d132",
			"parentId": "5c6687d65e9d882c8841f121",
			"slotId": "pocket1",
			"location": {
				"x": 0,
				"y": 0,
				"r": "Horizontal"
			},
			"upd": {
				"SpawnedInSession": true
			}
		},
		{
			"_id": "Pocket_778105",
			"_tpl": "5d40425986f7743185265461",
			"parentId": "5c6687d65e9d882c8841f121",
			"slotId": "pocket2",
			"location": {
				"x": 0,
				"y": 0,
				"r": "Horizontal"
			},
			"upd": {
				"SpawnedInSession": true
			}
		},
		{
			"_id": "Pocket_302996",
			"_tpl": "5672c92d4bdc2d180f8b4567",
			"parentId": "5c6687d65e9d882c8841f121",
			"slotId": "pocket3",
			"location": {
				"x": 0,
				"y": 0,
				"r": "Horizontal"
			},
			"upd": {
				"SpawnedInSession": true
			}
		}
	],
	"equipment": "5c6687d65e9d882c8841f0fd",
	"stash": "5c6687d65e9d882c8841f0fc",
	"questRaidItems": "5c6687d65e9d882c8841f0fe",
	"questStashItems": "5c6687d65e9d882c8841f0ff",
	"fastPanel": {}
}